README.md
setup.cfg
setup.py
perks/DEV.py
perks/SETUP.py
perks/__init__.py
perks/old_perks.py
perks.egg-info/PKG-INFO
perks.egg-info/SOURCES.txt
perks.egg-info/dependency_links.txt
perks.egg-info/top_level.txt
perks/default/__init__.py
perks/default/baselog.py
perks/default/win.py
perks/flow/__init__.py
perks/flow/expression.py
perks/flow/filewrapper.py
perks/flow/shell.py
perks/sql/SQL.py
perks/sql/__init__.py
perks/system/__init__.py
perks/system/scanner.py
perks/task/__init__.py
perks/task/connection.py
perks/task/hacking.py
perks/task/process.py