Metadata-Version: 1.2
Name: perks
Version: 1.26.1
Summary: A powerful package that provide some interesting function
Home-page: https://github.com/Marco-Della-Putta/perks
Author: Marco Della Putta
Author-email: marcodp183@gmail.com
Maintainer: Marco Della Putta
Maintainer-email: marcodp183@gmail.com
License: GNU License
Platform: UNKNOWN
